{
  "First Group-PI": [
    {
      "name": "Taylor",
      "surname": "Davis"
    },
    {
      "name": "Isabella",
      "surname": "Scott"
    },
    {
      "name": "Chloe",
      "surname": "Woods"
    },
    {
      "name": "Ivan",
      "surname": "Richardson"
    },
    {
      "name": "Ivan",
      "surname": "Brown"
    },
    {
      "name": "Ella",
      "surname": "Brown"
    },
    {
      "name": "Elizabeth",
      "surname": "Scott"
    },
    {
      "name": "Peter",
      "surname": "Johnson"
    },
    {
      "name": "Randy",
      "surname": "Martin"
    },
    {
      "name": "Michael",
      "surname": "Phillips"
    },
    {
      "name": "Ed",
      "surname": "Brown"
    },
    {
      "name": "Luis",
      "surname": "Richardson"
    },
    {
      "name": "Ed",
      "surname": "Johnson"
    },
    {
      "name": "Gavin",
      "surname": "Garcia"
    },
    {
      "name": "Taylor",
      "surname": "Howard"
    },
    {
      "name": "Orlando",
      "surname": "Scott"
    },
    {
      "name": "Chloe",
      "surname": "Taylor"
    },
    {
      "name": "Jacob",
      "surname": "Hill"
    },
    {
      "name": "Paula",
      "surname": "Scott"
    },
    {
      "name": "Lily",
      "surname": "Miller"
    }
  ],
  "Second Group-BI": [
    {
      "name": "Taylor",
      "surname": "Davis"
    },
    {
      "name": "Isabella",
      "surname": "Scott"
    },
    {
      "name": "Chloe",
      "surname": "Woods"
    },
    {
      "name": "Ivan",
      "surname": "Richardson"
    },
    {
      "name": "Ivan",
      "surname": "Brown"
    },
    {
      "name": "Ella",
      "surname": "Brown"
    },
    {
      "name": "Elizabeth",
      "surname": "Scott"
    },
    {
      "name": "Peter",
      "surname": "Johnson"
    },
    {
      "name": "Randy",
      "surname": "Martin"
    },
    {
      "name": "Michael",
      "surname": "Phillips"
    },
    {
      "name": "Ed",
      "surname": "Brown"
    },
    {
      "name": "Luis",
      "surname": "Richardson"
    },
    {
      "name": "Ed",
      "surname": "Johnson"
    },
    {
      "name": "Gavin",
      "surname": "Garcia"
    },
    {
      "name": "Taylor",
      "surname": "Howard"
    },
    {
      "name": "Orlando",
      "surname": "Scott"
    },
    {
      "name": "Chloe",
      "surname": "Taylor"
    },
    {
      "name": "Jacob",
      "surname": "Hill"
    },
    {
      "name": "Paula",
      "surname": "Scott"
    },
    {
      "name": "Lily",
      "surname": "Miller"
    }
  ],
  "Third Group-PMI": [
    {
      "name": "Taylor",
      "surname": "Davis"
    },
    {
      "name": "Isabella",
      "surname": "Scott"
    },
    {
      "name": "Chloe",
      "surname": "Woods"
    },
    {
      "name": "Ivan",
      "surname": "Richardson"
    },
    {
      "name": "Ivan",
      "surname": "Brown"
    },
    {
      "name": "Ella",
      "surname": "Brown"
    },
    {
      "name": "Elizabeth",
      "surname": "Scott"
    },
    {
      "name": "Peter",
      "surname": "Johnson"
    },
    {
      "name": "Randy",
      "surname": "Martin"
    },
    {
      "name": "Michael",
      "surname": "Phillips"
    },
    {
      "name": "Ed",
      "surname": "Brown"
    },
    {
      "name": "Luis",
      "surname": "Richardson"
    },
    {
      "name": "Ed",
      "surname": "Johnson"
    },
    {
      "name": "Gavin",
      "surname": "Garcia"
    },
    {
      "name": "Taylor",
      "surname": "Howard"
    },
    {
      "name": "Orlando",
      "surname": "Scott"
    },
    {
      "name": "Chloe",
      "surname": "Taylor"
    },
    {
      "name": "Jacob",
      "surname": "Hill"
    },
    {
      "name": "Paula",
      "surname": "Scott"
    },
    {
      "name": "Lily",
      "surname": "Miller"
    }
  ]
}
